fourtest/__init__.py
fourtest/__init___enc.py
fourtest/api.py
fourtest/api_enc.py
fourtest/client.py
fourtest/client_enc.py
fourtest-0.1.7.dist-info/METADATA
fourtest-0.1.7.dist-info/WHEEL
fourtest-0.1.7.dist-info/entry_points.txt
fourtest-0.1.7.dist-info/top_level.txt
fourtest-0.1.7.dist-info/RECORD
